django_cdk/__init__.py
django_cdk/py.typed
django_cdk/_jsii/__init__.py
django_cdk/_jsii/django-cdk@0.0.29.jsii.tgz
django_cdk-0.0.29.dist-info/LICENSE
django_cdk-0.0.29.dist-info/METADATA
django_cdk-0.0.29.dist-info/WHEEL
django_cdk-0.0.29.dist-info/top_level.txt
django_cdk-0.0.29.dist-info/RECORD
