Metadata-Version: 2.1
Name: django-cdk
Version: 0.0.29
Summary: django-cdk
Home-page: https://github.com/briancaffey/django-cdk.git
Author: Brian Caffey<briancaffey2010@gmail.com>
License: Apache-2.0
Project-URL: Source, https://github.com/briancaffey/django-cdk.git
Platform: UNKNOWN
Classifier: Intended Audience :: Developers
Classifier: Operating System :: OS Independent
Classifier: Programming Language :: JavaScript
Classifier: Programming Language :: Python :: 3 :: Only
Classifier: Programming Language :: Python :: 3.6
Classifier: Programming Language :: Python :: 3.7
Classifier: Programming Language :: Python :: 3.8
Classifier: Programming Language :: Python :: 3.9
Classifier: Typing :: Typed
Classifier: Development Status :: 5 - Production/Stable
Classifier: License :: OSI Approved
Requires-Python: >=3.6
License-File: LICENSE
Requires-Dist: aws-cdk.aws-autoscaling (<2.0.0,>=1.134.0)
Requires-Dist: aws-cdk.aws-certificatemanager (<2.0.0,>=1.134.0)
Requires-Dist: aws-cdk.aws-cloudformation (<2.0.0,>=1.134.0)
Requires-Dist: aws-cdk.aws-cloudfront-origins (<2.0.0,>=1.134.0)
Requires-Dist: aws-cdk.aws-cloudfront (<2.0.0,>=1.134.0)
Requires-Dist: aws-cdk.aws-cloudwatch (<2.0.0,>=1.134.0)
Requires-Dist: aws-cdk.aws-ec2 (<2.0.0,>=1.134.0)
Requires-Dist: aws-cdk.aws-ecr-assets (<2.0.0,>=1.134.0)
Requires-Dist: aws-cdk.aws-ecr (<2.0.0,>=1.134.0)
Requires-Dist: aws-cdk.aws-ecs-patterns (<2.0.0,>=1.134.0)
Requires-Dist: aws-cdk.aws-ecs (<2.0.0,>=1.134.0)
Requires-Dist: aws-cdk.aws-efs (<2.0.0,>=1.134.0)
Requires-Dist: aws-cdk.aws-eks (<2.0.0,>=1.134.0)
Requires-Dist: aws-cdk.aws-elasticache (<2.0.0,>=1.134.0)
Requires-Dist: aws-cdk.aws-elasticloadbalancingv2 (<2.0.0,>=1.134.0)
Requires-Dist: aws-cdk.aws-events-targets (<2.0.0,>=1.134.0)
Requires-Dist: aws-cdk.aws-events (<2.0.0,>=1.134.0)
Requires-Dist: aws-cdk.aws-iam (<2.0.0,>=1.134.0)
Requires-Dist: aws-cdk.aws-kms (<2.0.0,>=1.134.0)
Requires-Dist: aws-cdk.aws-lambda (<2.0.0,>=1.134.0)
Requires-Dist: aws-cdk.aws-logs (<2.0.0,>=1.134.0)
Requires-Dist: aws-cdk.aws-rds (<2.0.0,>=1.134.0)
Requires-Dist: aws-cdk.aws-route53-targets (<2.0.0,>=1.134.0)
Requires-Dist: aws-cdk.aws-route53 (<2.0.0,>=1.134.0)
Requires-Dist: aws-cdk.aws-s3-deployment (<2.0.0,>=1.134.0)
Requires-Dist: aws-cdk.aws-s3 (<2.0.0,>=1.134.0)
Requires-Dist: aws-cdk.aws-secretsmanager (<2.0.0,>=1.134.0)
Requires-Dist: aws-cdk.aws-ssm (<2.0.0,>=1.134.0)
Requires-Dist: aws-cdk.core (<2.0.0,>=1.134.0)
Requires-Dist: aws-cdk.custom-resources (<2.0.0,>=1.134.0)
Requires-Dist: cdk8s (<2.0.0,>=1.0.0.b11)
Requires-Dist: constructs (<4.0.0,>=3.2.27)
Requires-Dist: jsii (<2.0.0,>=1.45.0)
Requires-Dist: publication (>=0.0.3)
